src/tastystyles/__init__.py
src/tastystyles/colors.py
src/tastystyles/styles.py
tastystyle-0.0.1.dist-info/METADATA
tastystyle-0.0.1.dist-info/WHEEL
tastystyle-0.0.1.dist-info/licenses/LICENSE
tastystyle-0.0.1.dist-info/RECORD
