Metadata-Version: 2.1
Name: tastystyle
Version: 0.0.1
Summary: a python package for styling the terminal. how original, i know.
Project-URL: Homepage, https://github.com/t4styl/tastystyles
Author: tastyl
License-File: LICENSE
Classifier: License :: OSI Approved :: MIT License
Classifier: Operating System :: OS Independent
Classifier: Programming Language :: Python :: 3
Requires-Python: >=3.7
